{
  "Version": "2012-10-17",
  "Statement": [
    {
      "Sid": "AthenaWorkgroupAccess",
      "Effect": "Allow",
      "Action": [
        "athena:StartQueryExecution",
        "athena:GetQueryExecution",
        "athena:GetQueryResults",
        "athena:StopQueryExecution",
        "athena:GetWorkGroup",
        "athena:ListWorkGroups",
        "athena:ListDatabases",
        "athena:ListTableMetadata",
        "athena:GetTableMetadata"
      ],
      "Resource": "*"
    },
    {
      "Sid": "S3ResultsBucket",
      "Effect": "Allow",
      "Action": [
        "s3:GetObject",
        "s3:PutObject",
        "s3:ListBucket"
      ],
      "Resource": [
        "arn:aws:s3:::lks-analytics-results-*",
        "arn:aws:s3:::lks-analytics-results-*/*"
      ]
    },
    {
      "Sid": "S3ProcessedDataRead",
      "Effect": "Allow",
      "Action": [
        "s3:GetObject",
        "s3:ListBucket"
      ],
      "Resource": [
        "arn:aws:s3:::lks-analytics-processed-*",
        "arn:aws:s3:::lks-analytics-processed-*/*"
      ]
    },
    {
      "Sid": "GlueCatalogRead",
      "Effect": "Allow",
      "Action": [
        "glue:GetDatabase",
        "glue:GetDatabases",
        "glue:GetTable",
        "glue:GetTables",
        "glue:GetPartitions"
      ],
      "Resource": "*"
    },
    {
      "Sid": "LakeFormationDataAccess",
      "Effect": "Allow",
      "Action": [
        "lakeformation:GetDataAccess"
      ],
      "Resource": "*"
    }
  ]
}
